pinr/__init__.py
pinr/__main__.py
pinr/model.py
pinr/templates/fs-aseg.yml
pinr-0.1.1.dist-info/LICENSE.md
pinr-0.1.1.dist-info/METADATA
pinr-0.1.1.dist-info/WHEEL
pinr-0.1.1.dist-info/entry_points.txt
pinr-0.1.1.dist-info/RECORD
