Metadata-Version: 2.1
Name: pinr
Version: 0.1.1
Summary: Python tools for Interoperable Neuromorphometry Reporting
Home-page: https://pypi.org/project/pinr
License: MIT
Author: CorticoMetrics
Author-email: ltirrell@corticometrics.com
Requires-Python: >=3.8,<4.0
Classifier: Development Status :: 1 - Planning
Classifier: License :: OSI Approved :: MIT License
Classifier: Natural Language :: English
Classifier: Operating System :: OS Independent
Classifier: Programming Language :: Python
Classifier: Programming Language :: Python :: 3
Classifier: Programming Language :: Python :: 3.8
Classifier: Programming Language :: Python :: 3.9
Classifier: Programming Language :: Python :: 3.10
Classifier: Programming Language :: Python :: 3.11
Classifier: Programming Language :: Python :: 3
Classifier: Programming Language :: Python :: 3.10
Classifier: Programming Language :: Python :: 3.8
Classifier: Programming Language :: Python :: 3.9
Requires-Dist: colormath (>=3.0.0,<4.0.0)
Requires-Dist: dicom2nifti (>=2.4.7,<3.0.0)
Requires-Dist: fhir-resources[all] (>=6.5.0,<7.0.0)
Requires-Dist: highdicom (>=0.20.0,<0.21.0)
Requires-Dist: nibabel (>=5.0.0,<6.0.0)
Requires-Dist: nilearn (>=0.10.0,<0.11.0)
Requires-Dist: pandas (>=1.5.2,<2.0.0)
Requires-Dist: pydicom (>=2.3.1,<3.0.0)
Requires-Dist: typer[all] (>=0.7.0,<0.8.0)
Project-URL: Documentation, https://pinr.readthedocs.io
Project-URL: Repository, https://github.com/ltirrell/pinr
